Jinja2_template_info-0.2.4.data/data/share/doc/jinja2_template_info/AUTHORS
Jinja2_template_info-0.2.4.data/data/share/doc/jinja2_template_info/COPYING
Jinja2_template_info-0.2.4.data/data/share/doc/jinja2_template_info/ChangeLog
Jinja2_template_info-0.2.4.data/data/share/doc/jinja2_template_info/README.rst
Jinja2_template_info-0.2.4.data/data/share/doc/jinja2_template_info/examples/test.html
jinja2_template_info/__init__.py
jinja2_template_info/py.typed
jinja2_template_info/template_info.html
Jinja2_template_info-0.2.4.dist-info/AUTHORS
Jinja2_template_info-0.2.4.dist-info/COPYING
Jinja2_template_info-0.2.4.dist-info/METADATA
Jinja2_template_info-0.2.4.dist-info/WHEEL
Jinja2_template_info-0.2.4.dist-info/top_level.txt
Jinja2_template_info-0.2.4.dist-info/RECORD
