Metadata-Version: 2.1
Name: Jinja2-template-info
Version: 0.2.4
Summary: Jinja2 Extension for template debugging.
Home-page: https://github.com/ondratu/jinja2-template-info
Author: Ondřej Tůma
Author-email: mcbig@zeropage.cz
License: BSD
Platform: UNKNOWN
Classifier: Development Status :: 5 - Production/Stable
Classifier: Intended Audience :: Developers
Classifier: License :: OSI Approved :: BSD License
Classifier: Operating System :: OS Independent
Classifier: Programming Language :: Python :: 3
Classifier: Topic :: Software Development :: Libraries
License-File: COPYING
License-File: AUTHORS
Requires-Dist: Jinja2 (>=3.0.0)
